jupyterlab_autoversion/__init__.py
jupyterlab_autoversion/extension.py
jupyterlab_autoversion/extension/install.json
jupyterlab_autoversion/extension/jupyterlab_autoversion.json
jupyterlab_autoversion/labextension/package.json
jupyterlab_autoversion/labextension/static/736.d1108442db305d2edcc1.js
jupyterlab_autoversion/labextension/static/746.b7efdb1e604c559c2d1c.js
jupyterlab_autoversion/labextension/static/871.86801616074c974ab65b.js
jupyterlab_autoversion/labextension/static/998.225d5e6399bf3d05ecdc.js
jupyterlab_autoversion/labextension/static/remoteEntry.99efc7ad91d46e5e5785.js
jupyterlab_autoversion/labextension/static/style.js
jupyterlab_autoversion/labextension/static/third-party-licenses.json
jupyterlab_autoversion/storage/__init__.py
jupyterlab_autoversion/storage/git/__init__.py
jupyterlab_autoversion/storage/git/diff.py
jupyterlab_autoversion/storage/git/handlers.py
jupyterlab_autoversion/storage/git/hook.py
jupyterlab_autoversion/storage/s3/__init__.py
jupyterlab_autoversion/storage/s3/handlers.py
jupyterlab_autoversion/storage/s3/hook.py
jupyterlab_autoversion/storage/sql/__init__.py
jupyterlab_autoversion/storage/sql/handlers.py
jupyterlab_autoversion/storage/sql/hook.py
jupyterlab_autoversion/tests/__init__.py
jupyterlab_autoversion/tests/test_all.py
jupyterlab_autoversion/tests/test_extension.py
jupyterlab_autoversion/tests/test_handlers.py
jupyterlab_autoversion/tests/test_init.py
jupyterlab_autoversion-0.4.0.data/data/etc/jupyter/jupyter_server_config.d/jupyterlab_autoversion.json
jupyterlab_autoversion-0.4.0.data/data/share/jupyter/labextensions/jupyterlab_autoversion/package.json
jupyterlab_autoversion-0.4.0.data/data/share/jupyter/labextensions/jupyterlab_autoversion/static/736.d1108442db305d2edcc1.js
jupyterlab_autoversion-0.4.0.data/data/share/jupyter/labextensions/jupyterlab_autoversion/static/746.b7efdb1e604c559c2d1c.js
jupyterlab_autoversion-0.4.0.dist-info/METADATA
jupyterlab_autoversion-0.4.0.dist-info/WHEEL
jupyterlab_autoversion-0.4.0.dist-info/licenses/LICENSE
jupyterlab_autoversion-0.4.0.dist-info/RECORD
