Metadata-Version: 2.3
Name: jupyterlab_autoversion
Version: 0.4.0
Summary: Automatically version jupyter notebooks on save
Project-URL: Repository, https://github.com/timkpaine/jupyterlab_autoversion
Project-URL: Homepage, https://github.com/timkpaine/jupyterlab_autoversion
Author: the jupyterlab_autoversion authors
License:                                  Apache License
License-File: LICENSE
Keywords: Jupyter,JupyterLab,JupyterLab Extension,Templates
Classifier: Development Status :: 4 - Beta
Classifier: Framework :: Jupyter
Classifier: Framework :: Jupyter :: JupyterLab
Classifier: License :: OSI Approved :: Apache Software License
Classifier: Programming Language :: Python
Classifier: Programming Language :: Python :: 3
Classifier: Programming Language :: Python :: 3.8
Classifier: Programming Language :: Python :: 3.9
Classifier: Programming Language :: Python :: 3.10
Classifier: Programming Language :: Python :: 3.11
Classifier: Programming Language :: Python :: 3.12
Requires-Python: >=3.7
Requires-Dist: gitpython>=2.1.11
Requires-Dist: jupyterlab<5,>=4
Requires-Dist: nbdime
Provides-Extra: develop
Requires-Dist: pytest; extra == 'develop'
Requires-Dist: pytest-cov; extra == 'develop'
Requires-Dist: ruff<0.5,>=0.3; extra == 'develop'
Requires-Dist: twine<5.2,>=5; extra == 'develop'
Provides-Extra: test
Requires-Dist: pytest; extra == 'test'
Requires-Dist: pytest-cov; extra == 'test'
